schemodel/__init__.py
schemodel/base_item.py
schemodel/model_mongo_t.py
schemodel/model_mysql_t.py
schemodel-1.1.1.dist-info/METADATA
schemodel-1.1.1.dist-info/WHEEL
schemodel-1.1.1.dist-info/entry_points.txt
schemodel-1.1.1.dist-info/top_level.txt
schemodel-1.1.1.dist-info/RECORD
